CHANGES.txt
LICENSE
MANIFEST.in
README.rst
setup.py
aiobotocore/__init__.py
aiobotocore/client.py
aiobotocore/config.py
aiobotocore/endpoint.py
aiobotocore/paginate.py
aiobotocore/session.py
aiobotocore_mirror.egg-info/PKG-INFO
aiobotocore_mirror.egg-info/SOURCES.txt
aiobotocore_mirror.egg-info/dependency_links.txt
aiobotocore_mirror.egg-info/requires.txt
aiobotocore_mirror.egg-info/top_level.txt