Metadata-Version: 1.1
Name: aiobotocore-mirror
Version: 0.0.4
Summary: UNKNOWN
Home-page: https://github.com/aio-libs/aiobotocore
Author: nhumrich
Author-email: nick@humrich.us
License: Apache 2
Download-URL: https://pypi.python.org/pypi/aiobotocore-mirror
Platform: UNKNOWN
Classifier: Intended Audience :: Developers
Classifier: Intended Audience :: System Administrators
Classifier: Programming Language :: Python :: 3
Classifier: Programming Language :: Python :: 3.4
Classifier: Programming Language :: Python :: 3.5
Classifier: Environment :: Web Environment
Classifier: Development Status :: 3 - Alpha
